setup.py
PySolarized.egg-info/PKG-INFO
PySolarized.egg-info/SOURCES.txt
PySolarized.egg-info/dependency_links.txt
PySolarized.egg-info/requires.txt
PySolarized.egg-info/top_level.txt
pysolarized/__init__.py
pysolarized/solr.py