Metadata-Version: 1.1
Name: PySolarized
Version: 1.4.1
Summary: A simple library for accessing Apache Solr full-text search engine. Allows updating and queries overmultiple cores.
Home-page: https://github.com/izacus/pysolarized
Author: Jernej Virag
Author-email: jernej@virag.si
License: MIT
Platform: UNKNOWN
Classifier: License :: OSI Approved :: MIT License
Classifier: Operating System :: OS Independent
Classifier: Programming Language :: Python
Classifier: Programming Language :: Python :: 3
Classifier: Topic :: Software Development :: Libraries
Classifier: Topic :: Internet :: WWW/HTTP :: Indexing/Search
